Metadata-Version: 1.0
Name: play-in-bots-vk
Version: 0.1.7
Summary: Бот, который играет за вас
Home-page: UNKNOWN
Author: UNKNOWN
Author-email: ruslan@rym9n.ru
License: UNKNOWN
Platform: UNKNOWN
